AUTHORS.txt
CHANGES.txt
LICENSE.txt
MANIFEST.in
README.rst
setup.py
ccp/__init__.py
ccp/client.py
ccp.egg-info/PKG-INFO
ccp.egg-info/SOURCES.txt
ccp.egg-info/dependency_links.txt
ccp.egg-info/not-zip-safe
ccp.egg-info/requires.txt
ccp.egg-info/top_level.txt