Metadata-Version: 1.1
Name: ccp
Version: 1.1
Summary: A Python client for the Changelog API
Home-page: http://github.com/woohgit/changelog-client-python
Author: Adam Papai
Author-email: wooh@wooh.hu
License: Copyright (c) 2014 Adam Papai.
